alphaclops/__init__.py
alphaclops/_compat.py
alphaclops/_compat_test.py
alphaclops/_doc.py
alphaclops/_import.py
alphaclops/_import_test.py
alphaclops/_version.py
alphaclops/_version_test.py
alphaclops/conftest.py
alphaclops/json_resolver_cache.py
alphaclops/py.typed
alphaclops/type_workarounds.py
alphaclops/circuits/__init__.py
alphaclops/circuits/_block_diagram_drawer.py
alphaclops/circuits/_block_diagram_drawer_test.py
alphaclops/circuits/_box_drawing_character_data.py
alphaclops/circuits/_box_drawing_character_data_test.py
alphaclops/circuits/_bucket_priority_queue.py
alphaclops/circuits/_bucket_priority_queue_test.py
alphaclops/circuits/circuit.py
alphaclops/circuits/circuit_operation.py
alphaclops/circuits/circuit_operation_test.py
alphaclops/circuits/circuit_test.py
alphaclops/circuits/frozen_circuit.py
alphaclops/circuits/frozen_circuit_test.py
alphaclops/circuits/insert_strategy.py
alphaclops/circuits/insert_strategy_test.py
alphaclops/circuits/moment.py
alphaclops/circuits/moment_test.py
alphaclops/circuits/optimization_pass.py
alphaclops/circuits/optimization_pass_test.py
alphaclops/circuits/qasm_output.py
alphaclops/circuits/qasm_output_test.py
alphaclops/circuits/text_diagram_drawer.py
alphaclops/circuits/text_diagram_drawer_test.py
alphaclops/contrib/__init__.py
alphaclops/contrib/json.py
alphaclops/contrib/json_test.py
alphaclops/contrib/acquaintance/__init__.py
alphaclops/contrib/acquaintance/bipartite.py
alphaclops/contrib/acquaintance/bipartite_test.py
alphaclops/contrib/acquaintance/devices.py
alphaclops/contrib/acquaintance/devices_test.py
alphaclops/contrib/acquaintance/executor.py
alphaclops/contrib/acquaintance/executor_test.py
alphaclops/contrib/acquaintance/gates.py
alphaclops/contrib/acquaintance/gates_test.py
alphaclops/contrib/acquaintance/inspection_utils.py
alphaclops/contrib/acquaintance/inspection_utils_test.py
alphaclops/contrib/acquaintance/mutation_utils.py
alphaclops/contrib/acquaintance/mutation_utils_test.py
alphaclops_core-1.2.0.dev0.dist-info/LICENSE
alphaclops_core-1.2.0.dev0.dist-info/METADATA
alphaclops_core-1.2.0.dev0.dist-info/WHEEL
alphaclops_core-1.2.0.dev0.dist-info/top_level.txt
alphaclops_core-1.2.0.dev0.dist-info/RECORD
