Metadata-Version: 2.1
Name: alphaclops-core
Version: 1.2.0.dev0
Summary: A framework for creating, editing, and invoking Noisy Intermediate Scale Quantum (NISQ) circuits.
Home-page: http://github.com/quantumlib/alphaclops
Author: The alphaclops Developers
Author-email: alphaclops-dev@googlegroups.com
License: Apache 2
Requires-Python: >=3.9.0
License-File: LICENSE
Requires-Dist: duet (~=0.2.8)
Requires-Dist: matplotlib (~=3.0)
Requires-Dist: networkx (>=2.4)
Requires-Dist: numpy (~=1.16)
Requires-Dist: pandas
Requires-Dist: sortedcontainers (~=2.0)
Requires-Dist: scipy
Requires-Dist: sympy
Requires-Dist: typing-extensions (>=4.2)
Requires-Dist: tqdm
Provides-Extra: contrib
Requires-Dist: ply (>=3.6) ; extra == 'contrib'
Requires-Dist: pylatex (~=1.3.0) ; extra == 'contrib'
Requires-Dist: quimb ; extra == 'contrib'
Requires-Dist: opt-einsum ; extra == 'contrib'
Requires-Dist: autoray ; extra == 'contrib'
Requires-Dist: numba (>=0.53.0) ; extra == 'contrib'
